emailutils/__init__.py
emailutils/cli.py
emailutils/emailutils.py
kai_emailutils-0.1.0.dist-info/licenses/AUTHORS.rst
kai_emailutils-0.1.0.dist-info/licenses/LICENSE
kai_emailutils-0.1.0.dist-info/METADATA
kai_emailutils-0.1.0.dist-info/WHEEL
kai_emailutils-0.1.0.dist-info/top_level.txt
kai_emailutils-0.1.0.dist-info/RECORD
