Metadata-Version: 2.4
Name: kai-emailutils
Version: 0.1.0
Summary: Helpful email stuff
Author-email: Kai Bellmann <kb@bellmann-engineering.com>
Maintainer-email: Kai Bellmann <kb@bellmann-engineering.com>
License: MIT license
Project-URL: bugs, https://github.com/beengineering/emailutils/issues
Project-URL: changelog, https://github.com/beengineering/emailutils/blob/master/changelog.md
Project-URL: homepage, https://github.com/beengineering/emailutils
License-File: LICENSE
License-File: AUTHORS.rst
Provides-Extra: dev
Requires-Dist: coverage; extra == "dev"
Requires-Dist: mypy; extra == "dev"
Requires-Dist: pytest; extra == "dev"
Requires-Dist: ruff; extra == "dev"
Dynamic: license-file
